dpt_module_loader/__init__.py
dpt_module_loader/abstract_loader.py
dpt_module_loader/class_loader.py
dpt_module_loader/loader.py
dpt_module_loader/named_class_loader.py
dpt_module_loader-1.0.6.data/data/docs/LICENSE
dpt_module_loader-1.0.6.data/data/docs/README
dpt_module_loader-1.0.6.dist-info/LICENSE
dpt_module_loader-1.0.6.dist-info/METADATA
dpt_module_loader-1.0.6.dist-info/WHEEL
dpt_module_loader-1.0.6.dist-info/top_level.txt
dpt_module_loader-1.0.6.dist-info/RECORD
