Metadata-Version: 2.1
Name: dpt-module-loader
Version: 1.0.6
Summary: Imports modules and classes dynamically by name
Home-page: https://www.direct-netware.de/redirect?dpt;module_loader
Author: direct Netware Group et al.
Author-email: web@direct-netware.de
License: MPL2
Platform: any
Classifier: Intended Audience :: Developers
Classifier: License :: OSI Approved :: Mozilla Public License 2.0 (MPL 2.0)
Classifier: Operating System :: OS Independent
Classifier: Programming Language :: Python
Classifier: Topic :: Software Development :: Libraries :: Python Modules
License-File: LICENSE
Requires-Dist: dpt-runtime (<3,>=2)
Requires-Dist: dpt-threading (<3,>=2)
